ErisPulse_XiaomiMarathon/Core.py
ErisPulse_XiaomiMarathon/__init__.py
erispulse_xiaomimarathon-1.0.0.dist-info/licenses/LICENSE
erispulse_xiaomimarathon-1.0.0.dist-info/METADATA
erispulse_xiaomimarathon-1.0.0.dist-info/WHEEL
erispulse_xiaomimarathon-1.0.0.dist-info/entry_points.txt
erispulse_xiaomimarathon-1.0.0.dist-info/top_level.txt
erispulse_xiaomimarathon-1.0.0.dist-info/RECORD
