Metadata-Version: 2.4
Name: ErisPulse-XiaomiMarathon
Version: 1.0.0
Summary: 小米马拉松模拟器
Author-email: wsu2059q <wsu2059@qq.com>
License: Copyright 2025 wsu2059q
Project-URL: homepage, https://github.com/wsu2059q/ErisPulse-XiaomiMarathon
Requires-Python: >=3.9
License-File: LICENSE
Dynamic: license-file
